obddaemon/__init__.py
obddaemon/__main__.py
obddaemon/daemon.py
obddaemon/dummy.py
obddaemon/errors.py
obddaemon/keys.py
obddaemon/custom/Obd2DataParser.py
obddaemon/custom/__init__.py
obddaemon/custom/daemon.py
obddaemon/custom/errors.py
carpi_obddaemon-0.3.1.dist-info/LICENSE
carpi_obddaemon-0.3.1.dist-info/METADATA
carpi_obddaemon-0.3.1.dist-info/WHEEL
carpi_obddaemon-0.3.1.dist-info/top_level.txt
carpi_obddaemon-0.3.1.dist-info/RECORD
